ftstore/__init__.py
ftstore/version.py
ftstore/datasets/__init__.py
ftstore/datasets/loader.py
ftstore/datasets/registry.py
ftstore/datasets/utils.py
ftstore/datasets/data/breast_cancer/metadata.json
ftstore/datasets/data/iris/iris.data
ftstore/datasets/data/iris/metadata.json
ftstore-0.1.0.dist-info/LICENSE
ftstore-0.1.0.dist-info/METADATA
ftstore-0.1.0.dist-info/WHEEL
ftstore-0.1.0.dist-info/entry_points.txt
ftstore-0.1.0.dist-info/top_level.txt
ftstore-0.1.0.dist-info/RECORD
