Metadata-Version: 2.1
Name: ftstore
Version: 0.1.0
Summary: Advanced local dataset management for machine learning
Home-page: https://github.com/chrisli-llb/ftstore
Author: chrisli-llb
Author-email: 871266889@qq.com
Project-URL: Bug Tracker, https://github.com/chrisli-llb/ftstore/issues
Project-URL: Documentation, https://github.com/chrisli-llb/ftstore/wiki
Project-URL: Source Code, https://github.com/chrisli-llb/ftstore
Classifier: Development Status :: 3 - Alpha
Classifier: Intended Audience :: Developers
Classifier: Intended Audience :: Science/Research
Classifier: License :: OSI Approved :: MIT License
Classifier: Programming Language :: Python :: 3
Classifier: Programming Language :: Python :: 3.7
Classifier: Programming Language :: Python :: 3.8
Classifier: Programming Language :: Python :: 3.9
Classifier: Programming Language :: Python :: 3.10
Classifier: Programming Language :: Python :: 3.11
Classifier: Operating System :: OS Independent
Classifier: Topic :: Scientific/Engineering :: Artificial Intelligence
Classifier: Topic :: Software Development :: Libraries :: Python Modules
Requires-Python: >=3.7
License-File: LICENSE
Requires-Dist: pandas>=1.0
Requires-Dist: numpy>=1.18
Requires-Dist: requests>=2.25
Requires-Dist: joblib>=1.0
Provides-Extra: dev
Requires-Dist: pytest>=6.0; extra == "dev"
Requires-Dist: pytest-cov>=3.0; extra == "dev"
Requires-Dist: twine>=4.0; extra == "dev"
Requires-Dist: wheel>=0.37; extra == "dev"
Requires-Dist: flake8>=4.0; extra == "dev"
Requires-Dist: black>=22.0; extra == "dev"
Provides-Extra: excel
Requires-Dist: openpyxl>=3.0; extra == "excel"
Requires-Dist: xlrd>=2.0; extra == "excel"
Provides-Extra: feather
Requires-Dist: pyarrow>=3.0; extra == "feather"
Provides-Extra: full
Requires-Dist: pyarrow>=3.0; extra == "full"
Requires-Dist: tables>=3.6; extra == "full"
Requires-Dist: openpyxl>=3.0; extra == "full"
Requires-Dist: xlrd>=2.0; extra == "full"
Provides-Extra: hdf5
Requires-Dist: tables>=3.6; extra == "hdf5"
Provides-Extra: parquet
Requires-Dist: pyarrow>=3.0; extra == "parquet"
